{"description": null, "readme": null, "prev_commits": ["fix", "bruh", "feat: updated pres", "feat:added dates", "chore: spr 2025 update", "feat; fixed type", "feat: updated quotes", "feat: added prompting presentation", "feat: updated dates + fixed typos", "feat: added presentation section", "feat: fixing typo in resume", "chore: i forgot how to spell but thats ok", "chore: updated resume", "feat: added ppl, updated resume", "feat: modified code", "feat: updated courses v2", "feat: new bakery unlocked", "feat: updated courses fall 2025", "feat: updated book", "feat: minor changes", "chore: updated course list", "chore: update aug 2024", "chore: format", "debug: minor changes", "debug: removing workflows", "Merge branch 'main' of github.com:Abuynits/my_website", "feat: build ws", "Create static.yml", "Create jekyll-gh-pages.yml", "feat: website changes"], "title": "Abuynits.github.io", "owner": "abuynits", "commits": 30}