{"description": "Using a novel approach of bound embeddings, using yolov9 to generate local information about objects in an image and then passing it to a classification model", "readme": "# Indoor Scene Recognition\nNovel approach of bound embeddings, using yolov9 to generate local information about objects in an image and then passing it to a pre-trained image classification model.", "prev_commits": ["Merge branch 'main' of https://github.com/harmya/indoor-scene-recognition", "lel", "added gitignore", "Merge branch 'main' of https://github.com/harmya/indoor-scene-recognition", "first", "Initial commit"], "title": "indoor-scene-recognition", "owner": "harmya", "commits": 6}